synxflow/__init__.py
synxflow/debris.cp311-win_amd64.pyd
synxflow/flood.cp311-win_amd64.pyd
synxflow/landslide.cp311-win_amd64.pyd
synxflow/version.py
synxflow/IO/Boundary.py
synxflow/IO/InputModel.py
synxflow/IO/Landcover.py
synxflow/IO/OutputModel.py
synxflow/IO/Rainfall.py
synxflow/IO/Raster.py
synxflow/IO/Summary.py
synxflow/IO/__init__.py
synxflow/IO/demo_functions.py
synxflow/IO/grid_show.py
synxflow/IO/indep_functions.py
synxflow/IO/rainfall_processing.py
synxflow/IO/spatial_analysis.py
synxflow/IO/sample/debris/DEM.txt
synxflow/IO/sample/debris/Erosion.txt
synxflow/IO/sample/flood/DEM.gz
synxflow/IO/sample/flood/landcover.gz
synxflow/IO/sample/flood/rain_mask.gz
synxflow/IO/sample/flood/rain_source.csv
synxflow/IO/sample/landslide/dem.gz
synxflow/IO/sample/landslide/depth.gz
synxflow-1.0.1.dist-info/LICENSE.txt
synxflow-1.0.1.dist-info/METADATA
synxflow-1.0.1.dist-info/WHEEL
synxflow-1.0.1.dist-info/authors.md
synxflow-1.0.1.dist-info/top_level.txt
synxflow-1.0.1.dist-info/RECORD
