Metadata-Version: 2.2
Name: synxflow
Version: 1.0.1
Summary: Simulating Mass Movement and Flood Inundation for Multi-hazard Risk Assessment
Author: Xilin Xia
Author-email: x.xia.1@bham.ac.uk
License: GPLv3
Classifier: Development Status :: 3 - Alpha
Classifier: License :: OSI Approved :: GNU General Public License v3 or later (GPLv3+)
Classifier: Programming Language :: Python :: 3.9
Classifier: Programming Language :: C++
Classifier: Intended Audience :: Science/Research
License-File: LICENSE.txt
License-File: authors.md
Requires-Dist: numpy
Requires-Dist: scipy
Requires-Dist: matplotlib
Requires-Dist: imageio
Requires-Dist: pandas
Requires-Dist: rasterio
Requires-Dist: pyshp
Requires-Dist: fiona
Dynamic: author
Dynamic: author-email
Dynamic: classifier
Dynamic: description
Dynamic: description-content-type
Dynamic: license
Dynamic: requires-dist
Dynamic: summary
